HomekitAppKaifaZhinan/README.md
HomekitAppKaifaZhinan/__init__.py
HomekitAppKaifaZhinan/__main__.py
HomekitAppKaifaZhinan/file.epub
HomekitAppKaifaZhinan/index.html
HomekitAppKaifaZhinan/css/__init__.py
HomekitAppKaifaZhinan/css/annotations.css
HomekitAppKaifaZhinan/css/main.css
HomekitAppKaifaZhinan/css/normalize.css
HomekitAppKaifaZhinan/css/popup.css
HomekitAppKaifaZhinan/font/__init__.py
HomekitAppKaifaZhinan/font/fontello.eot
HomekitAppKaifaZhinan/font/fontello.svg
HomekitAppKaifaZhinan/font/fontello.ttf
HomekitAppKaifaZhinan/font/fontello.woff
HomekitAppKaifaZhinan/img/__init__.py
HomekitAppKaifaZhinan/img/annotator-glyph-sprite.png
HomekitAppKaifaZhinan/img/annotator-icon-sprite.png
HomekitAppKaifaZhinan/img/apple-touch-icon.png
HomekitAppKaifaZhinan/img/cancelfullscreen.png
HomekitAppKaifaZhinan/img/close.png
HomekitAppKaifaZhinan/img/fullscreen.png
HomekitAppKaifaZhinan/img/loader.gif
HomekitAppKaifaZhinan/img/menu-icon.png
HomekitAppKaifaZhinan/img/save.png
HomekitAppKaifaZhinan/img/saved.png
HomekitAppKaifaZhinan/img/settings-s.png
HomekitAppKaifaZhinan/img/settings.png
HomekitAppKaifaZhinan/img/star.png
HomekitAppKaifaZhinan/js/__init__.py
HomekitAppKaifaZhinan/js/epub.js
HomekitAppKaifaZhinan/js/epub.min.js
HomekitAppKaifaZhinan/js/epub.min.map
HomekitAppKaifaZhinan/js/hooks.min.js
HomekitAppKaifaZhinan/js/hooks.min.map
HomekitAppKaifaZhinan/js/reader.js
HomekitAppKaifaZhinan/js/reader.js.map
HomekitAppKaifaZhinan/js/reader.min.js
HomekitAppKaifaZhinan/js/reader.min.map
HomekitAppKaifaZhinan/js/hooks/__init__.py
HomekitAppKaifaZhinan/js/hooks/extensions/__init__.py
HomekitAppKaifaZhinan/js/hooks/extensions/highlight.js
HomekitAppKaifaZhinan/js/libs/__init__.py
HomekitAppKaifaZhinan/js/libs/jquery.min.js
HomekitAppKaifaZhinan/js/libs/localforage.min.js
HomekitAppKaifaZhinan/js/libs/screenfull.js
HomekitAppKaifaZhinan/js/libs/screenfull.min.js
HomekitAppKaifaZhinan/js/libs/zip.min.js
HomekitAppKaifaZhinan/js/plugins/__init__.py
homekit_app_kaifa_zhinan-2024.3.2.0.dist-info/METADATA
homekit_app_kaifa_zhinan-2024.3.2.0.dist-info/WHEEL
homekit_app_kaifa_zhinan-2024.3.2.0.dist-info/entry_points.txt
homekit_app_kaifa_zhinan-2024.3.2.0.dist-info/top_level.txt
homekit_app_kaifa_zhinan-2024.3.2.0.dist-info/RECORD
